bnurbs.cpython-311-darwin.so
infinigen/__init__.py
infinigen/launch_blender.py
infinigen/OcMesher/__init__.py
infinigen/OcMesher/demo.py
infinigen/OcMesher/requirements.txt
infinigen/OcMesher/ocmesher/__init__.py
infinigen/OcMesher/ocmesher/core.py
infinigen/OcMesher/ocmesher/utils/__init__.py
infinigen/OcMesher/ocmesher/utils/interface.py
infinigen/OcMesher/ocmesher/utils/timer.py
infinigen/assets/__init__.py
infinigen/assets/cactus/__init__.py
infinigen/assets/cactus/base.py
infinigen/assets/cactus/columnar.py
infinigen/assets/cactus/generate.py
infinigen/assets/cactus/globular.py
infinigen/assets/cactus/kalidium.py
infinigen/assets/cactus/pricky_pear.py
infinigen/assets/cactus/spike.py
infinigen/assets/corals/__init__.py
infinigen/assets/corals/base.py
infinigen/assets/corals/diff_growth.py
infinigen/assets/corals/elkhorn.py
infinigen/assets/corals/fan.py
infinigen/assets/corals/generate.py
infinigen/assets/corals/laplacian.py
infinigen/assets/corals/reaction_diffusion.py
infinigen/assets/corals/star.py
infinigen/assets/corals/tentacles.py
infinigen/assets/corals/tree.py
infinigen/assets/corals/tube.py
infinigen/assets/creatures/__init__.py
infinigen/assets/creatures/beetle.py
infinigen/assets/creatures/bird.py
infinigen/assets/creatures/carnivore.py
infinigen/assets/creatures/crustacean.py
infinigen/assets/creatures/fish.py
infinigen/assets/creatures/herbivore.py
infinigen/assets/creatures/jellyfish.py
infinigen/assets/creatures/reptile.py
infinigen/assets/creatures/insects/__init__.py
infinigen/assets/creatures/insects/dragonfly.py
infinigen/assets/creatures/insects/parts/antenna/dragonfly_antenna.py
infinigen/assets/creatures/insects/parts/body/dragonfly_body.py
infinigen/assets/creatures/insects/parts/eye/dragonfly_eye.py
infinigen/assets/creatures/insects/parts/hair/principled_hair.py
infinigen/assets/creatures/insects/parts/head/dragonfly_head.py
infinigen/assets/creatures/insects/parts/leg/dragonfly_leg.py
rr_infinigen-1.3.4.dist-info/LICENSE
rr_infinigen-1.3.4.dist-info/METADATA
rr_infinigen-1.3.4.dist-info/WHEEL
rr_infinigen-1.3.4.dist-info/top_level.txt
rr_infinigen-1.3.4.dist-info/RECORD
