Metadata-Version: 2.1
Name: rr-infinigen
Version: 1.3.4
Summary: Infinite Photorealistic Worlds using Procedural Generation
License: BSD 3-Clause License
Keywords: computer vision,data generation,procedural
Classifier: Programming Language :: Python :: 3
Classifier: Programming Language :: Python :: 3.11
Requires-Python: ==3.11.*
License-File: LICENSE
Requires-Dist: bpy ==4.1.0
Requires-Dist: einops
Requires-Dist: flow-vis
Requires-Dist: frozendict
Requires-Dist: geomdl
Requires-Dist: gin-config >=0.5.0
Requires-Dist: imageio
Requires-Dist: matplotlib
Requires-Dist: numpy
Requires-Dist: opencv-python
Requires-Dist: psutil
Requires-Dist: scikit-image
Requires-Dist: scikit-learn
Requires-Dist: scipy
Requires-Dist: submitit
Requires-Dist: tqdm
Requires-Dist: trimesh
Requires-Dist: pandas
Requires-Dist: landlab >=2.6.0
Requires-Dist: pycparser
Requires-Dist: pyrender
Requires-Dist: vnoise
Provides-Extra: dev
Requires-Dist: pytest ; extra == 'dev'
Requires-Dist: pytest-ordering ; extra == 'dev'
Requires-Dist: pytest-cov ; extra == 'dev'
Requires-Dist: pytest-xdist ; extra == 'dev'
Requires-Dist: pytest-timeout ; extra == 'dev'
Requires-Dist: ruff ; extra == 'dev'
Provides-Extra: wandb
Requires-Dist: wandb ; extra == 'wandb'
